{
  "resolvedId": "C:/Users/.Freelancer/TICKET/node_modules/lucide-react/dist/esm/icons/corner-down-right.js",
  "transforms": [
    {
      "name": "vite:load-fallback",
      "result": "/**\n * @license lucide-react v0.510.0 - ISC\n *\n * This source code is licensed under the ISC license.\n * See the LICENSE file in the root directory of this source tree.\n */\n\nimport createLucideIcon from '../createLucideIcon.js';\n\nconst __iconNode = [\n  [\"polyline\", { points: \"15 10 20 15 15 20\", key: \"1q7qjw\" }],\n  [\"path\", { d: \"M4 4v7a4 4 0 0 0 4 4h12\", key: \"z08zvw\" }]\n];\nconst CornerDownRight = createLucideIcon(\"corner-down-right\", __iconNode);\n\nexport { __iconNode, CornerDownRight as default };\n//# sourceMappingURL=corner-down-right.js.map\n",
      "start": 1751267856372,
      "end": 1751267856579,
      "sourcemaps": null
    },
    {
      "name": "vite:react-babel",
      "start": 1751267856579,
      "end": 1751267856579,
      "order": "pre"
    },
    {
      "name": "vite:esbuild",
      "start": 1751267856579,
      "end": 1751267856579,
      "order": "normal"
    },
    {
      "name": "vite:worker",
      "start": 1751267856579,
      "end": 1751267856579,
      "order": "normal-normal"
    },
    {
      "name": "vite:define",
      "start": 1751267856579,
      "end": 1751267856579,
      "order": "normal-normal"
    },
    {
      "name": "vite:build-html",
      "start": 1751267856579,
      "end": 1751267856579,
      "order": "normal-normal"
    },
    {
      "name": "vite:worker-import-meta-url",
      "start": 1751267856580,
      "end": 1751267856580,
      "order": "normal-normal"
    },
    {
      "name": "vite:asset-import-meta-url",
      "start": 1751267856580,
      "end": 1751267856580,
      "order": "normal-normal"
    },
    {
      "name": "vite:dynamic-import-vars",
      "start": 1751267856580,
      "end": 1751267856580,
      "order": "normal-normal"
    },
    {
      "name": "vite:import-glob",
      "start": 1751267856580,
      "end": 1751267856580,
      "order": "normal-normal"
    },
    {
      "name": "vite:build-import-analysis",
      "start": 1751267856580,
      "end": 1751267856580,
      "order": "normal-normal"
    },
    {
      "name": "vite:reporter",
      "start": 1751267856580,
      "end": 1751267856580,
      "order": "normal"
    }
  ]
}
