{
  "resolvedId": "C:/Users/.Freelancer/TICKET/node_modules/framer-motion/dist/es/animation/animators/waapi/animate-style.mjs",
  "transforms": [
    {
      "name": "vite:load-fallback",
      "result": "import { GroupAnimationWithThen } from 'motion-dom';\nimport { animateElements } from './animate-elements.mjs';\n\nconst createScopedWaapiAnimate = (scope) => {\n    function scopedAnimate(elementOrSelector, keyframes, options) {\n        return new GroupAnimationWithThen(animateElements(elementOrSelector, keyframes, options, scope));\n    }\n    return scopedAnimate;\n};\nconst animateMini = /*@__PURE__*/ createScopedWaapiAnimate();\n\nexport { animateMini, createScopedWaapiAnimate };\n",
      "start": 1751092523277,
      "end": 1751092523849,
      "sourcemaps": null
    },
    {
      "name": "vite:react-babel",
      "start": 1751092523849,
      "end": 1751092523849,
      "order": "pre"
    },
    {
      "name": "vite:esbuild",
      "start": 1751092523849,
      "end": 1751092523849,
      "order": "normal"
    },
    {
      "name": "vite:worker",
      "start": 1751092523849,
      "end": 1751092523849,
      "order": "normal-normal"
    },
    {
      "name": "vite:define",
      "start": 1751092523849,
      "end": 1751092523849,
      "order": "normal-normal"
    },
    {
      "name": "vite:build-html",
      "start": 1751092523849,
      "end": 1751092523849,
      "order": "normal-normal"
    },
    {
      "name": "vite:worker-import-meta-url",
      "start": 1751092523849,
      "end": 1751092523849,
      "order": "normal-normal"
    },
    {
      "name": "vite:asset-import-meta-url",
      "start": 1751092523849,
      "end": 1751092523849,
      "order": "normal-normal"
    },
    {
      "name": "vite:dynamic-import-vars",
      "start": 1751092523849,
      "end": 1751092523849,
      "order": "normal-normal"
    },
    {
      "name": "vite:import-glob",
      "start": 1751092523849,
      "end": 1751092523849,
      "order": "normal-normal"
    },
    {
      "name": "vite:build-import-analysis",
      "start": 1751092523849,
      "end": 1751092523849,
      "order": "normal-normal"
    },
    {
      "name": "vite:reporter",
      "start": 1751092523849,
      "end": 1751092523849,
      "order": "normal"
    }
  ]
}
