{
  "resolvedId": "C:/Users/.Freelancer/ONLINE/node_modules/lucide-react/dist/esm/icons/chevrons-right-left.js",
  "transforms": [
    {
      "name": "vite:load-fallback",
      "result": "/**\n * @license lucide-react v0.510.0 - ISC\n *\n * This source code is licensed under the ISC license.\n * See the LICENSE file in the root directory of this source tree.\n */\n\nimport createLucideIcon from '../createLucideIcon.js';\n\nconst __iconNode = [\n  [\"path\", { d: \"m20 17-5-5 5-5\", key: \"30x0n2\" }],\n  [\"path\", { d: \"m4 17 5-5-5-5\", key: \"16spf4\" }]\n];\nconst ChevronsRightLeft = createLucideIcon(\"chevrons-right-left\", __iconNode);\n\nexport { __iconNode, ChevronsRightLeft as default };\n//# sourceMappingURL=chevrons-right-left.js.map\n",
      "start": 1751092516069,
      "end": 1751092516299,
      "sourcemaps": null
    },
    {
      "name": "vite:react-babel",
      "start": 1751092516299,
      "end": 1751092516299,
      "order": "pre"
    },
    {
      "name": "vite:esbuild",
      "start": 1751092516299,
      "end": 1751092516299,
      "order": "normal"
    },
    {
      "name": "vite:worker",
      "start": 1751092516299,
      "end": 1751092516299,
      "order": "normal-normal"
    },
    {
      "name": "vite:define",
      "start": 1751092516299,
      "end": 1751092516299,
      "order": "normal-normal"
    },
    {
      "name": "vite:build-html",
      "start": 1751092516299,
      "end": 1751092516299,
      "order": "normal-normal"
    },
    {
      "name": "vite:worker-import-meta-url",
      "start": 1751092516299,
      "end": 1751092516299,
      "order": "normal-normal"
    },
    {
      "name": "vite:asset-import-meta-url",
      "start": 1751092516299,
      "end": 1751092516299,
      "order": "normal-normal"
    },
    {
      "name": "vite:dynamic-import-vars",
      "start": 1751092516299,
      "end": 1751092516299,
      "order": "normal-normal"
    },
    {
      "name": "vite:import-glob",
      "start": 1751092516300,
      "end": 1751092516300,
      "order": "normal-normal"
    },
    {
      "name": "vite:build-import-analysis",
      "start": 1751092516300,
      "end": 1751092516300,
      "order": "normal-normal"
    },
    {
      "name": "vite:reporter",
      "start": 1751092516300,
      "end": 1751092516300,
      "order": "normal"
    }
  ]
}
