{
  "resolvedId": "C:/Users/.Freelancer/ONLINE/node_modules/@babel/runtime/helpers/esm/iterableToArray.js",
  "transforms": [
    {
      "name": "vite:load-fallback",
      "result": "function _iterableToArray(r) {\n  if (\"undefined\" != typeof Symbol && null != r[Symbol.iterator] || null != r[\"@@iterator\"]) return Array.from(r);\n}\nexport { _iterableToArray as default };",
      "start": 1751092503464,
      "end": 1751092503673,
      "sourcemaps": null
    },
    {
      "name": "vite:react-babel",
      "start": 1751092503673,
      "end": 1751092503673,
      "order": "pre"
    },
    {
      "name": "vite:esbuild",
      "start": 1751092503673,
      "end": 1751092503673,
      "order": "normal"
    },
    {
      "name": "vite:worker",
      "start": 1751092503673,
      "end": 1751092503673,
      "order": "normal-normal"
    },
    {
      "name": "vite:define",
      "start": 1751092503673,
      "end": 1751092503673,
      "order": "normal-normal"
    },
    {
      "name": "vite:build-html",
      "start": 1751092503673,
      "end": 1751092503673,
      "order": "normal-normal"
    },
    {
      "name": "vite:worker-import-meta-url",
      "start": 1751092503673,
      "end": 1751092503673,
      "order": "normal-normal"
    },
    {
      "name": "vite:asset-import-meta-url",
      "start": 1751092503673,
      "end": 1751092503673,
      "order": "normal-normal"
    },
    {
      "name": "vite:dynamic-import-vars",
      "start": 1751092503673,
      "end": 1751092503673,
      "order": "normal-normal"
    },
    {
      "name": "vite:import-glob",
      "start": 1751092503673,
      "end": 1751092503673,
      "order": "normal-normal"
    },
    {
      "name": "vite:build-import-analysis",
      "start": 1751092503673,
      "end": 1751092503673,
      "order": "normal-normal"
    },
    {
      "name": "vite:reporter",
      "start": 1751092503673,
      "end": 1751092503676,
      "order": "normal"
    }
  ]
}
