{
  "resolvedId": "C:/Users/.Freelancer/ONLINE/node_modules/react-icons/index.mjs",
  "transforms": [
    {
      "name": "vite:load-fallback",
      "result": "// THIS FILE IS AUTO GENERATED\nexport * from './lib/index.mjs';",
      "start": 1749894720231,
      "end": 1749894720454,
      "sourcemaps": null
    },
    {
      "name": "vite:react-babel",
      "start": 1749894720454,
      "end": 1749894720454,
      "order": "pre"
    },
    {
      "name": "vite:esbuild",
      "start": 1749894720454,
      "end": 1749894720454,
      "order": "normal"
    },
    {
      "name": "vite:worker",
      "start": 1749894720454,
      "end": 1749894720454,
      "order": "normal-normal"
    },
    {
      "name": "vite:define",
      "start": 1749894720454,
      "end": 1749894720454,
      "order": "normal-normal"
    },
    {
      "name": "vite:build-html",
      "start": 1749894720454,
      "end": 1749894720454,
      "order": "normal-normal"
    },
    {
      "name": "vite:worker-import-meta-url",
      "start": 1749894720454,
      "end": 1749894720454,
      "order": "normal-normal"
    },
    {
      "name": "vite:asset-import-meta-url",
      "start": 1749894720454,
      "end": 1749894720454,
      "order": "normal-normal"
    },
    {
      "name": "vite:dynamic-import-vars",
      "start": 1749894720454,
      "end": 1749894720454,
      "order": "normal-normal"
    },
    {
      "name": "vite:import-glob",
      "start": 1749894720455,
      "end": 1749894720455,
      "order": "normal-normal"
    },
    {
      "name": "vite:build-import-analysis",
      "start": 1749894720455,
      "end": 1749894720455,
      "order": "normal-normal"
    },
    {
      "name": "vite:reporter",
      "start": 1749894720455,
      "end": 1749894720455,
      "order": "normal"
    }
  ]
}
