{
  "resolvedId": "C:/Users/.Freelancer/ONLINE/node_modules/lucide-react/dist/esm/icons/file-chart-column.js",
  "transforms": [
    {
      "name": "vite:load-fallback",
      "result": "/**\n * @license lucide-react v0.510.0 - ISC\n *\n * This source code is licensed under the ISC license.\n * See the LICENSE file in the root directory of this source tree.\n */\n\nimport createLucideIcon from '../createLucideIcon.js';\n\nconst __iconNode = [\n  [\"path\", { d: \"M15 2H6a2 2 0 0 0-2 2v16a2 2 0 0 0 2 2h12a2 2 0 0 0 2-2V7Z\", key: \"1rqfz7\" }],\n  [\"path\", { d: \"M14 2v4a2 2 0 0 0 2 2h4\", key: \"tnqrlb\" }],\n  [\"path\", { d: \"M8 18v-1\", key: \"zg0ygc\" }],\n  [\"path\", { d: \"M12 18v-6\", key: \"17g6i2\" }],\n  [\"path\", { d: \"M16 18v-3\", key: \"j5jt4h\" }]\n];\nconst FileChartColumn = createLucideIcon(\"file-chart-column\", __iconNode);\n\nexport { __iconNode, FileChartColumn as default };\n//# sourceMappingURL=file-chart-column.js.map\n",
      "start": 1750088812992,
      "end": 1750088813121,
      "sourcemaps": null
    },
    {
      "name": "vite:react-babel",
      "start": 1750088813121,
      "end": 1750088813121,
      "order": "pre"
    },
    {
      "name": "vite:esbuild",
      "start": 1750088813121,
      "end": 1750088813121,
      "order": "normal"
    },
    {
      "name": "vite:worker",
      "start": 1750088813121,
      "end": 1750088813121,
      "order": "normal-normal"
    },
    {
      "name": "vite:define",
      "start": 1750088813121,
      "end": 1750088813121,
      "order": "normal-normal"
    },
    {
      "name": "vite:build-html",
      "start": 1750088813121,
      "end": 1750088813121,
      "order": "normal-normal"
    },
    {
      "name": "vite:worker-import-meta-url",
      "start": 1750088813121,
      "end": 1750088813121,
      "order": "normal-normal"
    },
    {
      "name": "vite:asset-import-meta-url",
      "start": 1750088813121,
      "end": 1750088813121,
      "order": "normal-normal"
    },
    {
      "name": "vite:dynamic-import-vars",
      "start": 1750088813121,
      "end": 1750088813121,
      "order": "normal-normal"
    },
    {
      "name": "vite:import-glob",
      "start": 1750088813121,
      "end": 1750088813121,
      "order": "normal-normal"
    },
    {
      "name": "vite:build-import-analysis",
      "start": 1750088813122,
      "end": 1750088813122,
      "order": "normal-normal"
    },
    {
      "name": "vite:reporter",
      "start": 1750088813122,
      "end": 1750088813122,
      "order": "normal"
    }
  ]
}
