{
  "resolvedId": "C:/Users/.Freelancer/mussedupin-0f2501a9a053b0e75502c49e74876d2dc852c693/src/components/Footer/Footer.jsx",
  "transforms": [
    {
      "name": "vite:load-fallback",
      "result": "import React, { useState } from \"react\";\nimport { FaFacebook, FaInstagram, FaLinkedin, FaYoutube } from \"react-icons/fa\";\nimport { SiTiktok } from \"react-icons/si\";\nimport { Link, useNavigate } from \"react-router-dom\";\nimport FeedbackModal from \"../FeedbackModal/FeedbackModal\";\nimport \"./Footer.css\";\n\nconst Footer = () => {\n  const [openSections, setOpenSections] = useState([]);\n  const [isFeedbackModalOpen, setIsFeedbackModalOpen] = useState(false);\n  const navigate = useNavigate();\n\n  const toggleSection = (index) => {\n    setOpenSections((prev) => {\n      if (prev.includes(index)) {\n        return prev.filter((i) => i !== index);\n      } else {\n        return [...prev, index];\n      }\n    });\n  };\n\n  const handleContactClick = (e) => {\n    e.preventDefault();\n    navigate(\"/about\");\n    setTimeout(() => {\n      const element = document.getElementById(\"contact-section\");\n      if (element) {\n        element.scrollIntoView({ behavior: \"smooth\" });\n      }\n    }, 100);\n  };\n\n  return (\n    <>\n      <footer className=\"site-footer\">\n        <div className=\"footer-content\">\n          <div className=\"footer-sections\">\n            {/* About Section */}\n            <div\n              className={`footer-section ${\n                openSections.includes(0) ? \"open\" : \"\"\n              }`}\n            >\n              <h3 className=\"footer-heading\" onClick={() => toggleSection(0)}>\n                GIỚI THIỆU\n              </h3>\n              <ul className=\"footer-links\">\n                <li>\n                  <Link to=\"/about\">Bảo tàng Du Pin tại Việt Nam</Link>\n                </li>\n                <li>\n                  <Link to=\"/visitor-rules\">Nội quy tham quan</Link>\n                </li>\n              </ul>\n            </div>\n\n            {/* Our Websites Section */}\n            <div\n              className={`footer-section ${\n                openSections.includes(1) ? \"open\" : \"\"\n              }`}\n            >\n              <h3 className=\"footer-heading\" onClick={() => toggleSection(1)}>\n                TRANG WEB CỦA CHÚNG TÔI\n              </h3>\n              <ul className=\"footer-links\">\n                <li>\n                  <Link to=\"https://ticket-museeduphin.netlify.app/\">\n                    Dịch vụ đặt vé trực tuyến\n                  </Link>\n                </li>\n                <li>\n                  <Link to=\"https://online-museeduphin.netlify.app/\">\n                    Cửa hàng trực tuyến\n                  </Link>\n                </li>\n                <li>\n                  <Link to=\"/collection\">Bộ sưu tập</Link>\n                </li>\n              </ul>\n            </div>\n\n            {/* Contact Section */}\n            <div\n              className={`footer-section ${\n                openSections.includes(2) ? \"open\" : \"\"\n              }`}\n            >\n              <h3 className=\"footer-heading\" onClick={() => toggleSection(2)}>\n                LIÊN HỆ\n              </h3>\n              <ul className=\"footer-links\">\n                <li>\n                  <Link\n                    to=\"/visit-info#faq\"\n                    onClick={(e) => {\n                      e.preventDefault();\n                      navigate(\"/visit-info#faq\");\n                    }}\n                  >\n                    Câu hỏi thường gặp\n                  </Link>\n                </li>\n                <li>\n                  <a href=\"#\" onClick={handleContactClick}>\n                    Liên hệ với chúng tôi\n                  </a>\n                </li>\n                <li>\n                  <a\n                    href=\"#\"\n                    onClick={(e) => {\n                      e.preventDefault();\n                      setIsFeedbackModalOpen(true);\n                    }}\n                  >\n                    Gửi phản hồi cho chúng tôi!\n                  </a>\n                </li>\n              </ul>\n            </div>\n\n            {/* Follow Us Section */}\n            <div\n              className={`footer-section social-section ${\n                openSections.includes(3) ? \"open\" : \"\"\n              }`}\n            >\n              <h3 className=\"footer-heading\" onClick={() => toggleSection(3)}>\n                THEO DÕI CHÚNG TÔI\n              </h3>\n              <div className=\"social-icons\">\n                <a\n                  href=\"https://www.facebook.com/BaoTangThongDalat\"\n                  target=\"_blank\"\n                  rel=\"noopener noreferrer\"\n                  aria-label=\"Facebook\"\n                >\n                  <FaFacebook />\n                </a>\n                <a\n                  href=\"https://www.tiktok.com/@baotangthongdalat?_t=ZS-8wcfw9TGrnm&_r=1\"\n                  target=\"_blank\"\n                  rel=\"noopener noreferrer\"\n                  aria-label=\"TikTok\"\n                >\n                  <SiTiktok />\n                </a>\n                <a\n                  href=\"https://www.youtube.com/channel/UCyxLbhgBPZ3KnGD_KeLCo9A\"\n                  target=\"_blank\"\n                  rel=\"noopener noreferrer\"\n                  aria-label=\"YouTube\"\n                >\n                  <FaYoutube />\n                </a>\n              </div>\n            </div>\n          </div>\n\n          {/* Bottom Legal Links */}\n          <div className=\"footer-legal\">\n            <div className=\"legal-links\">\n              <Link to=\"/legal-notice\">Thông báo pháp lý</Link>\n              <Link to=\"/privacy-policy\">Chính sách bảo mật</Link>\n              <Link to=\"/copyrights\">Bản quyền</Link>\n            </div>\n          </div>\n\n          {/* Logo */}\n          <div className=\"footer-logo\">\n            <Link to=\"/\">\n              <img\n                src=\"https://res.cloudinary.com/dn0br7hj0/image/upload/v1748784840/logo/icon.png\"\n                alt=\"Logo Bảo tàng Du Pin\"\n              />\n            </Link>\n          </div>\n        </div>\n      </footer>\n\n      <FeedbackModal\n        isOpen={isFeedbackModalOpen}\n        onClose={() => setIsFeedbackModalOpen(false)}\n      />\n    </>\n  );\n};\n\nexport default Footer;\n",
      "start": 1750951454024,
      "end": 1750951454079,
      "sourcemaps": null
    },
    {
      "name": "vite:react-babel",
      "start": 1750951454079,
      "end": 1750951454079,
      "order": "pre"
    },
    {
      "name": "vite:esbuild",
      "result": "import { Fragment, jsx, jsxs } from \"react/jsx-runtime\";\nimport React, { useState } from \"react\";\nimport { FaFacebook, FaInstagram, FaLinkedin, FaYoutube } from \"react-icons/fa\";\nimport { SiTiktok } from \"react-icons/si\";\nimport { Link, useNavigate } from \"react-router-dom\";\nimport FeedbackModal from \"../FeedbackModal/FeedbackModal\";\nimport \"./Footer.css\";\nconst Footer = () => {\n  const [openSections, setOpenSections] = useState([]);\n  const [isFeedbackModalOpen, setIsFeedbackModalOpen] = useState(false);\n  const navigate = useNavigate();\n  const toggleSection = (index) => {\n    setOpenSections((prev) => {\n      if (prev.includes(index)) {\n        return prev.filter((i) => i !== index);\n      } else {\n        return [...prev, index];\n      }\n    });\n  };\n  const handleContactClick = (e) => {\n    e.preventDefault();\n    navigate(\"/about\");\n    setTimeout(() => {\n      const element = document.getElementById(\"contact-section\");\n      if (element) {\n        element.scrollIntoView({ behavior: \"smooth\" });\n      }\n    }, 100);\n  };\n  return /* @__PURE__ */ jsxs(Fragment, { children: [\n    /* @__PURE__ */ jsx(\"footer\", { className: \"site-footer\", children: /* @__PURE__ */ jsxs(\"div\", { className: \"footer-content\", children: [\n      /* @__PURE__ */ jsxs(\"div\", { className: \"footer-sections\", children: [\n        /* @__PURE__ */ jsxs(\n          \"div\",\n          {\n            className: `footer-section ${openSections.includes(0) ? \"open\" : \"\"}`,\n            children: [\n              /* @__PURE__ */ jsx(\"h3\", { className: \"footer-heading\", onClick: () => toggleSection(0), children: \"GIỚI THIỆU\" }),\n              /* @__PURE__ */ jsxs(\"ul\", { className: \"footer-links\", children: [\n                /* @__PURE__ */ jsx(\"li\", { children: /* @__PURE__ */ jsx(Link, { to: \"/about\", children: \"Bảo tàng Du Pin tại Việt Nam\" }) }),\n                /* @__PURE__ */ jsx(\"li\", { children: /* @__PURE__ */ jsx(Link, { to: \"/visitor-rules\", children: \"Nội quy tham quan\" }) })\n              ] })\n            ]\n          }\n        ),\n        /* @__PURE__ */ jsxs(\n          \"div\",\n          {\n            className: `footer-section ${openSections.includes(1) ? \"open\" : \"\"}`,\n            children: [\n              /* @__PURE__ */ jsx(\"h3\", { className: \"footer-heading\", onClick: () => toggleSection(1), children: \"TRANG WEB CỦA CHÚNG TÔI\" }),\n              /* @__PURE__ */ jsxs(\"ul\", { className: \"footer-links\", children: [\n                /* @__PURE__ */ jsx(\"li\", { children: /* @__PURE__ */ jsx(Link, { to: \"https://ticket-museeduphin.netlify.app/\", children: \"Dịch vụ đặt vé trực tuyến\" }) }),\n                /* @__PURE__ */ jsx(\"li\", { children: /* @__PURE__ */ jsx(Link, { to: \"https://online-museeduphin.netlify.app/\", children: \"Cửa hàng trực tuyến\" }) }),\n                /* @__PURE__ */ jsx(\"li\", { children: /* @__PURE__ */ jsx(Link, { to: \"/collection\", children: \"Bộ sưu tập\" }) })\n              ] })\n            ]\n          }\n        ),\n        /* @__PURE__ */ jsxs(\n          \"div\",\n          {\n            className: `footer-section ${openSections.includes(2) ? \"open\" : \"\"}`,\n            children: [\n              /* @__PURE__ */ jsx(\"h3\", { className: \"footer-heading\", onClick: () => toggleSection(2), children: \"LIÊN HỆ\" }),\n              /* @__PURE__ */ jsxs(\"ul\", { className: \"footer-links\", children: [\n                /* @__PURE__ */ jsx(\"li\", { children: /* @__PURE__ */ jsx(\n                  Link,\n                  {\n                    to: \"/visit-info#faq\",\n                    onClick: (e) => {\n                      e.preventDefault();\n                      navigate(\"/visit-info#faq\");\n                    },\n                    children: \"Câu hỏi thường gặp\"\n                  }\n                ) }),\n                /* @__PURE__ */ jsx(\"li\", { children: /* @__PURE__ */ jsx(\"a\", { href: \"#\", onClick: handleContactClick, children: \"Liên hệ với chúng tôi\" }) }),\n                /* @__PURE__ */ jsx(\"li\", { children: /* @__PURE__ */ jsx(\n                  \"a\",\n                  {\n                    href: \"#\",\n                    onClick: (e) => {\n                      e.preventDefault();\n                      setIsFeedbackModalOpen(true);\n                    },\n                    children: \"Gửi phản hồi cho chúng tôi!\"\n                  }\n                ) })\n              ] })\n            ]\n          }\n        ),\n        /* @__PURE__ */ jsxs(\n          \"div\",\n          {\n            className: `footer-section social-section ${openSections.includes(3) ? \"open\" : \"\"}`,\n            children: [\n              /* @__PURE__ */ jsx(\"h3\", { className: \"footer-heading\", onClick: () => toggleSection(3), children: \"THEO DÕI CHÚNG TÔI\" }),\n              /* @__PURE__ */ jsxs(\"div\", { className: \"social-icons\", children: [\n                /* @__PURE__ */ jsx(\n                  \"a\",\n                  {\n                    href: \"https://www.facebook.com/BaoTangThongDalat\",\n                    target: \"_blank\",\n                    rel: \"noopener noreferrer\",\n                    \"aria-label\": \"Facebook\",\n                    children: /* @__PURE__ */ jsx(FaFacebook, {})\n                  }\n                ),\n                /* @__PURE__ */ jsx(\n                  \"a\",\n                  {\n                    href: \"https://www.tiktok.com/@baotangthongdalat?_t=ZS-8wcfw9TGrnm&_r=1\",\n                    target: \"_blank\",\n                    rel: \"noopener noreferrer\",\n                    \"aria-label\": \"TikTok\",\n                    children: /* @__PURE__ */ jsx(SiTiktok, {})\n                  }\n                ),\n                /* @__PURE__ */ jsx(\n                  \"a\",\n                  {\n                    href: \"https://www.youtube.com/channel/UCyxLbhgBPZ3KnGD_KeLCo9A\",\n                    target: \"_blank\",\n                    rel: \"noopener noreferrer\",\n                    \"aria-label\": \"YouTube\",\n                    children: /* @__PURE__ */ jsx(FaYoutube, {})\n                  }\n                )\n              ] })\n            ]\n          }\n        )\n      ] }),\n      /* @__PURE__ */ jsx(\"div\", { className: \"footer-legal\", children: /* @__PURE__ */ jsxs(\"div\", { className: \"legal-links\", children: [\n        /* @__PURE__ */ jsx(Link, { to: \"/legal-notice\", children: \"Thông báo pháp lý\" }),\n        /* @__PURE__ */ jsx(Link, { to: \"/privacy-policy\", children: \"Chính sách bảo mật\" }),\n        /* @__PURE__ */ jsx(Link, { to: \"/copyrights\", children: \"Bản quyền\" })\n      ] }) }),\n      /* @__PURE__ */ jsx(\"div\", { className: \"footer-logo\", children: /* @__PURE__ */ jsx(Link, { to: \"/\", children: /* @__PURE__ */ jsx(\n        \"img\",\n        {\n          src: \"https://res.cloudinary.com/dn0br7hj0/image/upload/v1748784840/logo/icon.png\",\n          alt: \"Logo Bảo tàng Du Pin\"\n        }\n      ) }) })\n    ] }) }),\n    /* @__PURE__ */ jsx(\n      FeedbackModal,\n      {\n        isOpen: isFeedbackModalOpen,\n        onClose: () => setIsFeedbackModalOpen(false)\n      }\n    )\n  ] });\n};\nexport default Footer;\n",
      "start": 1750951454079,
      "end": 1750951454177,
      "order": "normal",
      "sourcemaps": {
        "version": 3,
        "sources": [
          "C:/Users/.Freelancer/mussedupin-0f2501a9a053b0e75502c49e74876d2dc852c693/src/components/Footer/Footer.jsx"
        ],
        "sourcesContent": [
          "import React, { useState } from \"react\";\nimport { FaFacebook, FaInstagram, FaLinkedin, FaYoutube } from \"react-icons/fa\";\nimport { SiTiktok } from \"react-icons/si\";\nimport { Link, useNavigate } from \"react-router-dom\";\nimport FeedbackModal from \"../FeedbackModal/FeedbackModal\";\nimport \"./Footer.css\";\n\nconst Footer = () => {\n  const [openSections, setOpenSections] = useState([]);\n  const [isFeedbackModalOpen, setIsFeedbackModalOpen] = useState(false);\n  const navigate = useNavigate();\n\n  const toggleSection = (index) => {\n    setOpenSections((prev) => {\n      if (prev.includes(index)) {\n        return prev.filter((i) => i !== index);\n      } else {\n        return [...prev, index];\n      }\n    });\n  };\n\n  const handleContactClick = (e) => {\n    e.preventDefault();\n    navigate(\"/about\");\n    setTimeout(() => {\n      const element = document.getElementById(\"contact-section\");\n      if (element) {\n        element.scrollIntoView({ behavior: \"smooth\" });\n      }\n    }, 100);\n  };\n\n  return (\n    <>\n      <footer className=\"site-footer\">\n        <div className=\"footer-content\">\n          <div className=\"footer-sections\">\n            {/* About Section */}\n            <div\n              className={`footer-section ${\n                openSections.includes(0) ? \"open\" : \"\"\n              }`}\n            >\n              <h3 className=\"footer-heading\" onClick={() => toggleSection(0)}>\n                GIỚI THIỆU\n              </h3>\n              <ul className=\"footer-links\">\n                <li>\n                  <Link to=\"/about\">Bảo tàng Du Pin tại Việt Nam</Link>\n                </li>\n                <li>\n                  <Link to=\"/visitor-rules\">Nội quy tham quan</Link>\n                </li>\n              </ul>\n            </div>\n\n            {/* Our Websites Section */}\n            <div\n              className={`footer-section ${\n                openSections.includes(1) ? \"open\" : \"\"\n              }`}\n            >\n              <h3 className=\"footer-heading\" onClick={() => toggleSection(1)}>\n                TRANG WEB CỦA CHÚNG TÔI\n              </h3>\n              <ul className=\"footer-links\">\n                <li>\n                  <Link to=\"https://ticket-museeduphin.netlify.app/\">\n                    Dịch vụ đặt vé trực tuyến\n                  </Link>\n                </li>\n                <li>\n                  <Link to=\"https://online-museeduphin.netlify.app/\">\n                    Cửa hàng trực tuyến\n                  </Link>\n                </li>\n                <li>\n                  <Link to=\"/collection\">Bộ sưu tập</Link>\n                </li>\n              </ul>\n            </div>\n\n            {/* Contact Section */}\n            <div\n              className={`footer-section ${\n                openSections.includes(2) ? \"open\" : \"\"\n              }`}\n            >\n              <h3 className=\"footer-heading\" onClick={() => toggleSection(2)}>\n                LIÊN HỆ\n              </h3>\n              <ul className=\"footer-links\">\n                <li>\n                  <Link\n                    to=\"/visit-info#faq\"\n                    onClick={(e) => {\n                      e.preventDefault();\n                      navigate(\"/visit-info#faq\");\n                    }}\n                  >\n                    Câu hỏi thường gặp\n                  </Link>\n                </li>\n                <li>\n                  <a href=\"#\" onClick={handleContactClick}>\n                    Liên hệ với chúng tôi\n                  </a>\n                </li>\n                <li>\n                  <a\n                    href=\"#\"\n                    onClick={(e) => {\n                      e.preventDefault();\n                      setIsFeedbackModalOpen(true);\n                    }}\n                  >\n                    Gửi phản hồi cho chúng tôi!\n                  </a>\n                </li>\n              </ul>\n            </div>\n\n            {/* Follow Us Section */}\n            <div\n              className={`footer-section social-section ${\n                openSections.includes(3) ? \"open\" : \"\"\n              }`}\n            >\n              <h3 className=\"footer-heading\" onClick={() => toggleSection(3)}>\n                THEO DÕI CHÚNG TÔI\n              </h3>\n              <div className=\"social-icons\">\n                <a\n                  href=\"https://www.facebook.com/BaoTangThongDalat\"\n                  target=\"_blank\"\n                  rel=\"noopener noreferrer\"\n                  aria-label=\"Facebook\"\n                >\n                  <FaFacebook />\n                </a>\n                <a\n                  href=\"https://www.tiktok.com/@baotangthongdalat?_t=ZS-8wcfw9TGrnm&_r=1\"\n                  target=\"_blank\"\n                  rel=\"noopener noreferrer\"\n                  aria-label=\"TikTok\"\n                >\n                  <SiTiktok />\n                </a>\n                <a\n                  href=\"https://www.youtube.com/channel/UCyxLbhgBPZ3KnGD_KeLCo9A\"\n                  target=\"_blank\"\n                  rel=\"noopener noreferrer\"\n                  aria-label=\"YouTube\"\n                >\n                  <FaYoutube />\n                </a>\n              </div>\n            </div>\n          </div>\n\n          {/* Bottom Legal Links */}\n          <div className=\"footer-legal\">\n            <div className=\"legal-links\">\n              <Link to=\"/legal-notice\">Thông báo pháp lý</Link>\n              <Link to=\"/privacy-policy\">Chính sách bảo mật</Link>\n              <Link to=\"/copyrights\">Bản quyền</Link>\n            </div>\n          </div>\n\n          {/* Logo */}\n          <div className=\"footer-logo\">\n            <Link to=\"/\">\n              <img\n                src=\"https://res.cloudinary.com/dn0br7hj0/image/upload/v1748784840/logo/icon.png\"\n                alt=\"Logo Bảo tàng Du Pin\"\n              />\n            </Link>\n          </div>\n        </div>\n      </footer>\n\n      <FeedbackModal\n        isOpen={isFeedbackModalOpen}\n        onClose={() => setIsFeedbackModalOpen(false)}\n      />\n    </>\n  );\n};\n\nexport default Footer;\n"
        ],
        "mappings": "AAkCI,mBAUU,KAGA,YAbV;AAlCJ,OAAO,SAAS,gBAAgB;AAChC,SAAS,YAAY,aAAa,YAAY,iBAAiB;AAC/D,SAAS,gBAAgB;AACzB,SAAS,MAAM,mBAAmB;AAClC,OAAO,mBAAmB;AAC1B,OAAO;AAEP,MAAM,SAAS,MAAM;AACnB,QAAM,CAAC,cAAc,eAAe,IAAI,SAAS,CAAC,CAAC;AACnD,QAAM,CAAC,qBAAqB,sBAAsB,IAAI,SAAS,KAAK;AACpE,QAAM,WAAW,YAAY;AAE7B,QAAM,gBAAgB,CAAC,UAAU;AAC/B,oBAAgB,CAAC,SAAS;AACxB,UAAI,KAAK,SAAS,KAAK,GAAG;AACxB,eAAO,KAAK,OAAO,CAAC,MAAM,MAAM,KAAK;AAAA,MACvC,OAAO;AACL,eAAO,CAAC,GAAG,MAAM,KAAK;AAAA,MACxB;AAAA,IACF,CAAC;AAAA,EACH;AAEA,QAAM,qBAAqB,CAAC,MAAM;AAChC,MAAE,eAAe;AACjB,aAAS,QAAQ;AACjB,eAAW,MAAM;AACf,YAAM,UAAU,SAAS,eAAe,iBAAiB;AACzD,UAAI,SAAS;AACX,gBAAQ,eAAe,EAAE,UAAU,SAAS,CAAC;AAAA,MAC/C;AAAA,IACF,GAAG,GAAG;AAAA,EACR;AAEA,SACE,iCACE;AAAA,wBAAC,YAAO,WAAU,eAChB,+BAAC,SAAI,WAAU,kBACb;AAAA,2BAAC,SAAI,WAAU,mBAEb;AAAA;AAAA,UAAC;AAAA;AAAA,YACC,WAAW,kBACT,aAAa,SAAS,CAAC,IAAI,SAAS,EACtC;AAAA,YAEA;AAAA,kCAAC,QAAG,WAAU,kBAAiB,SAAS,MAAM,cAAc,CAAC,GAAG,wBAEhE;AAAA,cACA,qBAAC,QAAG,WAAU,gBACZ;AAAA,oCAAC,QACC,8BAAC,QAAK,IAAG,UAAS,0CAA4B,GAChD;AAAA,gBACA,oBAAC,QACC,8BAAC,QAAK,IAAG,kBAAiB,+BAAiB,GAC7C;AAAA,iBACF;AAAA;AAAA;AAAA,QACF;AAAA,QAGA;AAAA,UAAC;AAAA;AAAA,YACC,WAAW,kBACT,aAAa,SAAS,CAAC,IAAI,SAAS,EACtC;AAAA,YAEA;AAAA,kCAAC,QAAG,WAAU,kBAAiB,SAAS,MAAM,cAAc,CAAC,GAAG,qCAEhE;AAAA,cACA,qBAAC,QAAG,WAAU,gBACZ;AAAA,oCAAC,QACC,8BAAC,QAAK,IAAG,2CAA0C,uCAEnD,GACF;AAAA,gBACA,oBAAC,QACC,8BAAC,QAAK,IAAG,2CAA0C,iCAEnD,GACF;AAAA,gBACA,oBAAC,QACC,8BAAC,QAAK,IAAG,eAAc,wBAAU,GACnC;AAAA,iBACF;AAAA;AAAA;AAAA,QACF;AAAA,QAGA;AAAA,UAAC;AAAA;AAAA,YACC,WAAW,kBACT,aAAa,SAAS,CAAC,IAAI,SAAS,EACtC;AAAA,YAEA;AAAA,kCAAC,QAAG,WAAU,kBAAiB,SAAS,MAAM,cAAc,CAAC,GAAG,qBAEhE;AAAA,cACA,qBAAC,QAAG,WAAU,gBACZ;AAAA,oCAAC,QACC;AAAA,kBAAC;AAAA;AAAA,oBACC,IAAG;AAAA,oBACH,SAAS,CAAC,MAAM;AACd,wBAAE,eAAe;AACjB,+BAAS,iBAAiB;AAAA,oBAC5B;AAAA,oBACD;AAAA;AAAA,gBAED,GACF;AAAA,gBACA,oBAAC,QACC,8BAAC,OAAE,MAAK,KAAI,SAAS,oBAAoB,mCAEzC,GACF;AAAA,gBACA,oBAAC,QACC;AAAA,kBAAC;AAAA;AAAA,oBACC,MAAK;AAAA,oBACL,SAAS,CAAC,MAAM;AACd,wBAAE,eAAe;AACjB,6CAAuB,IAAI;AAAA,oBAC7B;AAAA,oBACD;AAAA;AAAA,gBAED,GACF;AAAA,iBACF;AAAA;AAAA;AAAA,QACF;AAAA,QAGA;AAAA,UAAC;AAAA;AAAA,YACC,WAAW,iCACT,aAAa,SAAS,CAAC,IAAI,SAAS,EACtC;AAAA,YAEA;AAAA,kCAAC,QAAG,WAAU,kBAAiB,SAAS,MAAM,cAAc,CAAC,GAAG,gCAEhE;AAAA,cACA,qBAAC,SAAI,WAAU,gBACb;AAAA;AAAA,kBAAC;AAAA;AAAA,oBACC,MAAK;AAAA,oBACL,QAAO;AAAA,oBACP,KAAI;AAAA,oBACJ,cAAW;AAAA,oBAEX,8BAAC,cAAW;AAAA;AAAA,gBACd;AAAA,gBACA;AAAA,kBAAC;AAAA;AAAA,oBACC,MAAK;AAAA,oBACL,QAAO;AAAA,oBACP,KAAI;AAAA,oBACJ,cAAW;AAAA,oBAEX,8BAAC,YAAS;AAAA;AAAA,gBACZ;AAAA,gBACA;AAAA,kBAAC;AAAA;AAAA,oBACC,MAAK;AAAA,oBACL,QAAO;AAAA,oBACP,KAAI;AAAA,oBACJ,cAAW;AAAA,oBAEX,8BAAC,aAAU;AAAA;AAAA,gBACb;AAAA,iBACF;AAAA;AAAA;AAAA,QACF;AAAA,SACF;AAAA,MAGA,oBAAC,SAAI,WAAU,gBACb,+BAAC,SAAI,WAAU,eACb;AAAA,4BAAC,QAAK,IAAG,iBAAgB,+BAAiB;AAAA,QAC1C,oBAAC,QAAK,IAAG,mBAAkB,gCAAkB;AAAA,QAC7C,oBAAC,QAAK,IAAG,eAAc,uBAAS;AAAA,SAClC,GACF;AAAA,MAGA,oBAAC,SAAI,WAAU,eACb,8BAAC,QAAK,IAAG,KACP;AAAA,QAAC;AAAA;AAAA,UACC,KAAI;AAAA,UACJ,KAAI;AAAA;AAAA,MACN,GACF,GACF;AAAA,OACF,GACF;AAAA,IAEA;AAAA,MAAC;AAAA;AAAA,QACC,QAAQ;AAAA,QACR,SAAS,MAAM,uBAAuB,KAAK;AAAA;AAAA,IAC7C;AAAA,KACF;AAEJ;AAEA,eAAe;",
        "names": []
      }
    },
    {
      "name": "vite:worker",
      "start": 1750951454177,
      "end": 1750951454177,
      "order": "normal-normal"
    },
    {
      "name": "vite:define",
      "start": 1750951454177,
      "end": 1750951454177,
      "order": "normal-normal"
    },
    {
      "name": "vite:build-html",
      "start": 1750951454177,
      "end": 1750951454177,
      "order": "normal-normal"
    },
    {
      "name": "vite:worker-import-meta-url",
      "start": 1750951454178,
      "end": 1750951454178,
      "order": "normal-normal"
    },
    {
      "name": "vite:asset-import-meta-url",
      "start": 1750951454178,
      "end": 1750951454178,
      "order": "normal-normal"
    },
    {
      "name": "vite:dynamic-import-vars",
      "start": 1750951454178,
      "end": 1750951454178,
      "order": "normal-normal"
    },
    {
      "name": "vite:import-glob",
      "start": 1750951454178,
      "end": 1750951454178,
      "order": "normal-normal"
    },
    {
      "name": "vite:build-import-analysis",
      "start": 1750951454178,
      "end": 1750951454178,
      "order": "normal-normal"
    },
    {
      "name": "vite:reporter",
      "start": 1750951454178,
      "end": 1750951454178,
      "order": "normal"
    }
  ]
}
