{
  "resolvedId": "C:/Users/.Freelancer/ONLINE/node_modules/@babel/runtime/helpers/esm/arrayLikeToArray.js",
  "transforms": [
    {
      "name": "vite:load-fallback",
      "result": "function _arrayLikeToArray(r, a) {\n  (null == a || a > r.length) && (a = r.length);\n  for (var e = 0, n = Array(a); e < a; e++) n[e] = r[e];\n  return n;\n}\nexport { _arrayLikeToArray as default };",
      "start": 1750088805685,
      "end": 1750088805900,
      "sourcemaps": null
    },
    {
      "name": "vite:react-babel",
      "start": 1750088805900,
      "end": 1750088805900,
      "order": "pre"
    },
    {
      "name": "vite:esbuild",
      "start": 1750088805900,
      "end": 1750088805900,
      "order": "normal"
    },
    {
      "name": "vite:worker",
      "start": 1750088805900,
      "end": 1750088805900,
      "order": "normal-normal"
    },
    {
      "name": "vite:define",
      "start": 1750088805900,
      "end": 1750088805900,
      "order": "normal-normal"
    },
    {
      "name": "vite:build-html",
      "start": 1750088805900,
      "end": 1750088805900,
      "order": "normal-normal"
    },
    {
      "name": "vite:worker-import-meta-url",
      "start": 1750088805900,
      "end": 1750088805900,
      "order": "normal-normal"
    },
    {
      "name": "vite:asset-import-meta-url",
      "start": 1750088805900,
      "end": 1750088805900,
      "order": "normal-normal"
    },
    {
      "name": "vite:dynamic-import-vars",
      "start": 1750088805901,
      "end": 1750088805901,
      "order": "normal-normal"
    },
    {
      "name": "vite:import-glob",
      "start": 1750088805901,
      "end": 1750088805901,
      "order": "normal-normal"
    },
    {
      "name": "vite:build-import-analysis",
      "start": 1750088805901,
      "end": 1750088805901,
      "order": "normal-normal"
    },
    {
      "name": "vite:reporter",
      "start": 1750088805901,
      "end": 1750088805901,
      "order": "normal"
    }
  ]
}
